icb/__init__.py
icb/__version__.py
icb/constant.py
icb/data/db.csv
icb/data/pls.mod-scikit-learn-1.1.1-python-3.10.0.joblib
icb/helper/__init__.py
icb/helper/bash.py
icb/helper/chem_helper.py
icb/helper/db/__init__.py
icb/helper/db/smiles.py
icb/helper/kallisto_helper.py
icb/helper/ml/__init__.py
icb/helper/ml/data.py
icb/helper/rdkit_helper.py
icb/helper/ts/__init__.py
icb/helper/ts/store.py
icb/helper/utility.py
icb/helper/xtb_helper.py
icb/main/__init__.py
icb/main/header.py
icb/main/main.py
icb/main/results.py
icb/task/__init__.py
icb/task/create_barriers.py
icb/task/create_boltzmann_weight_image.py
icb/task/create_ch.py
icb/task/create_graph_deltas.py
icb/task/create_ml_deltas.py
icb/task/create_ts.py
icb/task/create_xtb_deltas.py
icb/task/optimize_structure.py
icb/task/sort_ch.py
icb/types.py
icb/utility.py
sobo-0.2.0.dist-info/entry_points.txt
sobo-0.2.0.dist-info/WHEEL
sobo-0.2.0.dist-info/METADATA
sobo-0.2.0.dist-info/RECORD
